core/__init__.py
core/main.py
core/version.py
prefiq_installer-1.1.9.dist-info/licenses/LICENSE
prefiq_installer-1.1.9.dist-info/METADATA
prefiq_installer-1.1.9.dist-info/WHEEL
prefiq_installer-1.1.9.dist-info/entry_points.txt
prefiq_installer-1.1.9.dist-info/top_level.txt
prefiq_installer-1.1.9.dist-info/RECORD
